{"description":"Deberia actualizar una cancha|workspace-project Cancha","passed":true,"pending":false,"os":"Windows","instanceId":3828,"browser":{"name":"chrome","version":"89.0.4389.82"},"message":"Passed","browserLogs":[{"level":"SEVERE","message":"http://localhost:4200/main.js 619:27 \"Error inesperado:\\n\" Object","timestamp":1615825449726,"type":""},{"level":"SEVERE","message":"http://localhost:4200/main.js 619:27 \"Error inesperado:\\n\" Object","timestamp":1615825449730,"type":""},{"level":"SEVERE","message":"http://localhost:4200/main.js 619:27 \"Error inesperado:\\n\" Object","timestamp":1615825450018,"type":""},{"level":"SEVERE","message":"http://localhost:4200/main.js 619:27 \"Error inesperado:\\n\" Object","timestamp":1615825450085,"type":""},{"level":"SEVERE","message":"http://localhost:4200/main.js 619:27 \"Error inesperado:\\n\" Object","timestamp":1615825450088,"type":""},{"level":"SEVERE","message":"http://localhost:4200/main.js 619:27 \"Error inesperado:\\n\" Object","timestamp":1615825450091,"type":""}],"screenShotFile":"00570068-0045-0042-006d-00e500470087.png","timestamp":1615825448980,"duration":1115}
